README.md
setup.py
iam_starter/__init__.py
iam_starter/__main__.py
iam_starter/aws_iam_utils.py
iam_starter/aws_util_exceptions.py
iam_starter/iam_starter.py
iam_starter/version.py
iam_starter.egg-info/PKG-INFO
iam_starter.egg-info/SOURCES.txt
iam_starter.egg-info/dependency_links.txt
iam_starter.egg-info/entry_points.txt
iam_starter.egg-info/requires.txt
iam_starter.egg-info/top_level.txt