Metadata-Version: 1.1
Name: iam-starter
Version: 0.1.2
Summary: A CLI which starts your program in the context of an assumed AWS IAM Role
Home-page: https://github.com/billtrust/iam-starter
Author: Doug Kerwin
Author-email: dwkerwin@gmail.com
License: MIT
Keywords: aws-iam,aws-iam-role
Platform: UNKNOWN
Classifier: Intended Audience :: Developers
Classifier: Natural Language :: English
Classifier: License :: OSI Approved :: MIT License
Classifier: Programming Language :: Python
Classifier: Programming Language :: Python :: 2
Classifier: Programming Language :: Python :: 2.7
Classifier: Programming Language :: Python :: 3
Classifier: Programming Language :: Python :: 3.6
